uniconnapps/connector/__init__.py
uniconnapps/connector/actions.py
uniconnapps/connector/core.py
uniconnapps/connector/events.py
uniconnapps/connector/utils.py
uniconnapps_connector-0.0.1a4.dist-info/LICENSE
uniconnapps_connector-0.0.1a4.dist-info/METADATA
uniconnapps_connector-0.0.1a4.dist-info/NOTICE
uniconnapps_connector-0.0.1a4.dist-info/WHEEL
uniconnapps_connector-0.0.1a4.dist-info/top_level.txt
uniconnapps_connector-0.0.1a4.dist-info/RECORD
