Metadata-Version: 2.1
Name: uniconnapps-connector
Version: 0.0.1a4
Summary: uniconnapps-connector
Author: Uniconnapps
Author-email: oss-maintainers@uniconnapps.com
License: Apache License 2.0
Classifier: Development Status :: 3 - Alpha
Classifier: Intended Audience :: Developers
Classifier: Topic :: Software Development
Classifier: License :: OSI Approved :: Apache Software License
Classifier: Programming Language :: Python
Classifier: Programming Language :: Python :: 3
Classifier: Programming Language :: Python :: 3.7
Classifier: Programming Language :: Python :: 3.8
Classifier: Programming Language :: Python :: 3.9
Classifier: Programming Language :: Python :: 3.10
Classifier: Programming Language :: Python :: 3.11
Requires-Python: >= 3.7
License-File: LICENSE
License-File: NOTICE
Requires-Dist: uniconnapps-connector-proto~=0.0.1a2
Requires-Dist: PyJWT>=2.4.0
